useless_test_package/__init__.py
useless_test_package/hulu.py
useless_test_package/main.py
useless_test_package-1.0.0.dist-info/METADATA
useless_test_package-1.0.0.dist-info/WHEEL
useless_test_package-1.0.0.dist-info/entry_points.txt
useless_test_package-1.0.0.dist-info/RECORD
