Metadata-Version: 2.1
Name: useless-test-package
Version: 1.0.0
Summary: 
Author: Lieven Spur
Requires-Python: >=3.10,<3.13
Classifier: Programming Language :: Python :: 3
Classifier: Programming Language :: Python :: 3.10
Classifier: Programming Language :: Python :: 3.11
Requires-Dist: humanize (>=4.8.0,<5.0.0)
